Metadata-Version: 2.4
Name: wpdm-kdobiczek
Version: 0.1.0
Summary: Warsztat Praktyka Data Mining
Author-email: Szymon Bobek <szymon.bobek@gmail.com>
License: MIT License
Project-URL: Homepage, https://github.com/sbobek/wpdm
Project-URL: Documentation, https://wpdm.readthedocs.org
Project-URL: Issues, https://github.com/sbobek/wpdm/issues
Keywords: xai,time-series,explainability,model-agnostic,rule-based
Classifier: License :: OSI Approved :: MIT License
Classifier: Programming Language :: Python
Classifier: Programming Language :: Python :: 3
Requires-Python: >=3.8
License-File: LICENSE
Requires-Dist: pandas>=1.4.3
Requires-Dist: numpy>=1.22.4
Requires-Dist: scikit-learn>=1.1.1
Requires-Dist: matplotlib>=3.5.2
Requires-Dist: matplotlib-inline>=0.1.3
Requires-Dist: seaborn>=0.11.2
Provides-Extra: gpu
Requires-Dist: torch>=2.0.1; extra == "gpu"
Dynamic: license-file
